pyflowcl/Clients.py
pyflowcl/Payment.py
pyflowcl/Refund.py
pyflowcl/__init__.py
pyflowcl/exceptions.py
pyflowcl/models.py
pyflowcl/version.py
pyflowcl-2025.2.0.dist-info/LICENSE
pyflowcl-2025.2.0.dist-info/METADATA
pyflowcl-2025.2.0.dist-info/WHEEL
pyflowcl-2025.2.0.dist-info/RECORD
