Metadata-Version: 2.3
Name: pyflowcl
Version: 2025.2.0
Summary: Cliente para comunicacion con API de flow.cl
License: MIT
Keywords: pagos,pagar,cobrar,ecommerce,tarjetas,credito,debito,flow
Author: Mario Hernandez
Author-email: mariofix@proton.me
Requires-Python: >=3.9, <4.0
Classifier: Development Status :: 5 - Production/Stable
Classifier: License :: OSI Approved :: MIT License
Classifier: Programming Language :: Python :: 3.9
Classifier: Programming Language :: Python :: 3.10
Classifier: Programming Language :: Python :: 3.11
Classifier: Programming Language :: Python :: 3.12
Classifier: Intended Audience :: Developers
Classifier: Topic :: Software Development :: Libraries :: Python Modules
Provides-Extra: dev
Requires-Dist: black (>=24.10.0,<25.0.0) ; extra == "dev"
Requires-Dist: coverage (>=7.6.10,<8.0.0) ; extra == "dev"
Requires-Dist: mkdocs-git-authors-plugin (>=0.9.2,<0.10.0) ; extra == "dev"
Requires-Dist: mkdocs-material[git,imaging,recomended] (>=9.5.50,<10.0.0) ; extra == "dev"
Requires-Dist: mkdocstrings[python] (>=0.27.0,<0.28.0) ; extra == "dev"
Requires-Dist: pre-commit (>=4.1.0,<5.0.0) ; extra == "dev"
Requires-Dist: pytest (>=8.3.4,<9.0.0) ; extra == "dev"
Requires-Dist: pytest-cov (>=6.0.0,<7.0.0) ; extra == "dev"
Requires-Dist: requests[security] (>=2.32.3,<3.0.0)
Project-URL: Documentation, https://mariofix.github.io/pyflowcl
Project-URL: Homepage, https://www.flow.cl/docs/api.html
Project-URL: Repository, https://github.com/mariofix/pyflowcl
